contrai/__init__.py
contrai/data/__init__.py
contrai/data/goes16.py
contrai/models/__init__.py
contrai/models/semantic_segmentation/__init__.py
contrai/models/semantic_segmentation/coat/CoaT_U.py
contrai/models/semantic_segmentation/coat/__init__.py
contrai/models/semantic_segmentation/coat/coat.py
contrai/models/semantic_segmentation/coat/weight_loader.py
contrai/utils/__init__.py
contrai/utils/plot.py
contrai/utils/predict.py
contrai/utils/tools.py
contrai/utils/vis.py
contrai-0.1.50.dist-info/LICENSE
contrai-0.1.50.dist-info/METADATA
contrai-0.1.50.dist-info/WHEEL
contrai-0.1.50.dist-info/top_level.txt
contrai-0.1.50.dist-info/RECORD
