Metadata-Version: 2.1
Name: Contrai
Version: 0.1.50
Summary: Detection and analysis of contrails using deep learning.
Home-page: https://github.com/irortiza/ContrAI
Author: Irene Ortiz
Author-email: irortiza@ing.uc3m.es
License: Apache-2.0
Classifier: Programming Language :: Python :: 3
Classifier: License :: OSI Approved :: Apache Software License
Classifier: Operating System :: OS Independent
Classifier: Development Status :: 3 - Alpha
Classifier: Intended Audience :: Science/Research
Classifier: Topic :: Scientific/Engineering :: Artificial Intelligence
Requires-Python: >=3.8
License-File: LICENSE
Requires-Dist: ipython==8.12.3
Requires-Dist: matplotlib==3.7.5
Requires-Dist: numpy==1.24.4
Requires-Dist: opencv-python==4.9.0.80
Requires-Dist: opencv-python-headless==4.9.0.80
Requires-Dist: Pillow
Requires-Dist: s3fs==2024.10.0
Requires-Dist: timm==0.9.2
Requires-Dist: torch==2.4.1
Requires-Dist: tqdm==4.65.2
Provides-Extra: dev
Requires-Dist: pytest; extra == "dev"
Requires-Dist: black; extra == "dev"
Requires-Dist: flake8; extra == "dev"
Requires-Dist: isort; extra == "dev"
